git996/__init__.py
git996/configer.py
git996/const.py
git996/main.py
git996/repor.py
git996/syncer.py
git996-0.0.2.dist-info/LICENSE
git996-0.0.2.dist-info/METADATA
git996-0.0.2.dist-info/WHEEL
git996-0.0.2.dist-info/entry_points.txt
git996-0.0.2.dist-info/top_level.txt
git996-0.0.2.dist-info/RECORD
